cloudquery/__init__.py
cloudquery/__main__.py
cloudquery/bin/cloudquery
py_cloudquery_linux_amd64-0.1.3.dist-info/METADATA
py_cloudquery_linux_amd64-0.1.3.dist-info/WHEEL
py_cloudquery_linux_amd64-0.1.3.dist-info/top_level.txt
py_cloudquery_linux_amd64-0.1.3.dist-info/RECORD
