Metadata-Version: 2.4
Name: py-cloudquery-linux-amd64
Version: 0.1.3
Summary: CloudQuery CLI for Linux amd64, bundled with the binary.
Author-email: CloudQuery <info@cloudquery.io>
Requires-Python: >=3.7
